smf/__init__.py
smf/core.py
smf/registry.py
smf/transport.py
smf/auth/__init__.py
smf/auth/policy.py
smf/auth/providers/__init__.py
smf/auth/providers/oidc.py
smf/cli/__init__.py
smf/cli/io.py
smf/cli/main.py
smf/cli/parser.py
smf/cli/commands/__init__.py
smf/cli/commands/run.py
smf/cli/commands/init/__init__.py
smf/cli/commands/init/command.py
smf/cli/commands/init/examples.py
smf/cli/commands/init/readme.py
smf/cli/commands/init/scaffold.py
smf/cli/commands/init/server.py
smf/cli/commands/init/settings.py
smf/cli/commands/init/structure.py
smf/cli/commands/init/template_loader.py
smf/cli/commands/init/templates/__init__.py
smf/cli/commands/init/templates/readme.tpl
smf/cli/commands/init/templates/server.tpl
smf/cli/commands/init/templates/tools.tpl
smf/cli/commands/inspector/__init__.py
smf/cli/commands/inspector/command.py
smf/plugins/__init__.py
smf/plugins/elasticsearch/__init__.py
smf/plugins/elasticsearch/connection.py
smf/plugins/elasticsearch/elasticsearch_configuration.py
smf/plugins/elasticsearch/env.py
smf/plugins/elasticsearch/requirements.py
smf/plugins/elasticsearch/settings.py
smf/plugins/elasticsearch/template_loader.py
smf/plugins/elasticsearch/version_check.py
smf/plugins/elasticsearch/templates/__init__.py
smf/plugins/elasticsearch/templates/elasticsearch.tpl
smf/plugins/elasticsearch/templates/env.tpl
smf/plugins/elasticsearch/templates/readme.tpl
smf/plugins/elasticsearch/templates/requirements.tpl
smf/plugins/elasticsearch/templates/server.tpl
smf/utils/cli.py
smf/utils/import_tools.py
smf_mcp-0.1.25.dist-info/METADATA
smf_mcp-0.1.25.dist-info/WHEEL
smf_mcp-0.1.25.dist-info/entry_points.txt
smf_mcp-0.1.25.dist-info/licenses/LICENSE
smf_mcp-0.1.25.dist-info/RECORD
