Metadata-Version: 2.4
Name: smf-mcp
Version: 0.1.25
Summary: Enterprise-grade MCP framework built on FastMCP
Project-URL: Homepage, https://github.com/guinat/smf-mcp
Project-URL: Repository, https://github.com/guinat/smf-mcp
Project-URL: Issues, https://github.com/guinat/smf-mcp/issues
Author: guinat
License: MIT License
License-File: LICENSE
Keywords: ai,enterprise,fastmcp,llm,mcp
Classifier: Development Status :: 3 - Alpha
Classifier: Intended Audience :: Developers
Classifier: License :: OSI Approved :: MIT License
Classifier: Programming Language :: Python :: 3
Classifier: Programming Language :: Python :: 3.11
Classifier: Programming Language :: Python :: 3.12
Classifier: Topic :: Software Development :: Libraries :: Python Modules
Requires-Python: <3.13,>=3.11
Requires-Dist: fastmcp<3,>=2.11
Requires-Dist: pydantic-settings<3,>=2
Requires-Dist: pydantic<3,>=2
Requires-Dist: python-dotenv>=1.0.0
Provides-Extra: elasticsearch7
Requires-Dist: elasticsearch<8,>=7; extra == 'elasticsearch7'
Provides-Extra: elasticsearch8
Requires-Dist: elasticsearch<9,>=8; extra == 'elasticsearch8'
Provides-Extra: elasticsearch9
Requires-Dist: elasticsearch<10,>=9; extra == 'elasticsearch9'
